{"id": "GUILD-BC107-BL34-BRAWL3", "format": "swiss", "sub_format": "brawl", "start_date": "2022-09-19T01:54:00.000Z", "status": 2, "data": {"duration_blocks": 57600, "multiple_rounds": false, "cp_min": 0, "spsp_min": 0, "group_size": 10, "create_team_seconds": 168, "challenge_level": 1, "guilds": ["4d379b1725b8ca17bc9a29d40bfe60735a7c1222", "969c06744e81863dd5c8c923e1cdd0ed0726ff49", "c85f07e6659ad1489ff86a2f2474bad81022b763", "b474a69eb936609e1bb4de38fd68038a59ee0e07", "8c2c80af29bfa09b266643cb5140953be69c3567", "62a375d44acd2ff4f19739e2d7ff82ab6ccd597a", "1e606081b97e373b9af4480704f0a4dd0c97efb7", "94818cc66694e83dadf5f63b221f1653f828c52f", "76ccf736f7e8939dfb9e893c3eb53035481eaa2b", "b5104f7a4ac1b26a8521bf67dac3b47c0d99d2db"], "crown_pot": 392}, "players": [{"total_battles": 9, "entered_battles": 9, "player": "mariajaimie", "join_date": "2022-09-17T03:00:57.000Z", "wins": 8, "losses": 1, "draws": 0, "finish": 4, "meta_pts": 186, "meta_pts_float": 2200, "defeated": "bronzebaby-shoes,joetunex,orissander,babyshark016,giuatt07,gandalfd,sarky,joserizal0425", "fray_index": 7, "brawl_level": 3, "player_data": {"player": "mariajaimie", "rating": 3121, "avatar_id": 0, "title_pre": null, "title_post": null, "display_name": null, "league": 3, "modern_league": 0, "collection_power": 8430, "starter_pack_purchase": true, "guild_id": "1e606081b97e373b9af4480704f0a4dd0c97efb7", "guild_rank": 2, "guild_join_date": "2022-03-07T14:13:21.000Z", "guild_status": "active"}}, {"total_battles": 8, "entered_battles": 8, "player": "jacko21", "join_date": "2022-09-17T03:30:03.000Z", "wins": 7, "losses": 1, "draws": 0, "finish": 9, "meta_pts": 150, "meta_pts_float": 2182, "defeated": "cryptomonica,pritongbutiki,lurefish1,reckesh,play-2-earn,graccus,textcrawl", "fray_index": 8, "brawl_level": 3, "player_data": {"player": "jacko21", "rating": 2800, "avatar_id": 9, "title_pre": null, "title_post": null, "display_name": null, "league": 10, "modern_league": 0, "collection_power": 571523, "starter_pack_purchase": true, "guild_id": "1e606081b97e373b9af4480704f0a4dd0c97efb7", "guild_rank": 2, "guild_join_date": "2021-12-11T21:21:33.000Z", "guild_status": "active"}}, {"total_battles": 9, "entered_battles": 9, "player": "investor777", "join_date": "2022-09-17T20:09:30.000Z", "wins": 7, "losses": 2, "draws": 0, "finish": 17, "meta_pts": 132, "meta_pts_float": 1900, "defeated": "wadetg,reaverza,vyse,road2horizon,king-of-rockets,ohliang,markespino", "fray_index": 6, "brawl_level": 3, "player_data": {"player": "investor777", "rating": 2334, "avatar_id": 0, "title_pre": null, "title_post": null, "display_name": null, "league": 8, "modern_league": 11, "collection_power": 620555, "starter_pack_purchase": true, "guild_id": "1e606081b97e373b9af4480704f0a4dd0c97efb7", "guild_rank": 4, "guild_join_date": "2021-09-28T00:10:18.000Z", "guild_status": "active"}}, {"total_battles": 8, "entered_battles": 8, "player": "deathangelfrey", "join_date": "2022-09-17T03:02:12.000Z", "wins": 6, "losses": 2, "draws": 0, "finish": 23, "meta_pts": 108, "meta_pts_float": 1901, "defeated": "sweetunicorn,tomarabi,sagesigma,rockaholik,mumpulls,cherrynator89", "fray_index": 11, "brawl_level": 3, "player_data": {"player": "deathangelfrey", "rating": 1960, "avatar_id": 9, "title_pre": null, "title_post": null, "display_name": null, "league": 7, "modern_league": 9, "collection_power": 353325, "starter_pack_purchase": true, "guild_id": "1e606081b97e373b9af4480704f0a4dd0c97efb7", "guild_rank": 1, "guild_join_date": "2022-05-10T16:01:48.000Z", "guild_status": "active"}}, {"total_battles": 9, "entered_battles": 9, "player": "denboxieval29", "join_date": "2022-09-17T06:20:03.000Z", "wins": 6, "losses": 3, "draws": 0, "finish": 29, "meta_pts": 156, "meta_pts_float": 0, "defeated": "shikiphantom,madbat,zurichhh,arc7icwolf,sageiris,teremirth", "fray_index": 1, "brawl_level": 3, "player_data": {"player": "denboxieval29", "rating": 0, "avatar_id": 1, "title_pre": null, "title_post": null, "display_name": null, "league": 0, "modern_league": 0, "collection_power": 43850, "starter_pack_purchase": true, "guild_id": "1e606081b97e373b9af4480704f0a4dd0c97efb7", "guild_rank": 3, "guild_join_date": "2021-09-25T22:35:00.000Z", "guild_status": "active"}}, {"total_battles": 8, "entered_battles": 8, "player": "thgaming", "join_date": "2022-09-18T04:39:06.000Z", "wins": 4, "losses": 4, "draws": 0, "finish": 68, "meta_pts": 78, "meta_pts_float": 245, "defeated": "nevashia,tipaklong,cryptoman976,michiel87", "fray_index": 12, "brawl_level": 3, "player_data": {"player": "thgaming", "rating": 754, "avatar_id": 0, "title_pre": null, "title_post": null, "display_name": null, "league": 3, "modern_league": 0, "collection_power": 69450, "starter_pack_purchase": true, "guild_id": "1e606081b97e373b9af4480704f0a4dd0c97efb7", "guild_rank": 1, "guild_join_date": "2022-07-25T14:03:12.000Z", "guild_status": "active"}}, {"total_battles": 9, "entered_battles": 9, "player": "jepoy0412", "join_date": "2022-09-18T00:41:06.000Z", "wins": 4, "losses": 5, "draws": 0, "finish": 79, "meta_pts": 90, "meta_pts_float": 2528, "defeated": "rayius,sidhu17,tjdemigod,alequandro", "fray_index": 0, "brawl_level": 3, "player_data": {"player": "jepoy0412", "rating": 1900, "avatar_id": 0, "title_pre": null, "title_post": null, "display_name": null, "league": 2, "modern_league": 0, "collection_power": 2240, "starter_pack_purchase": true, "guild_id": "1e606081b97e373b9af4480704f0a4dd0c97efb7", "guild_rank": 2, "guild_join_date": "2022-03-10T08:25:45.000Z", "guild_status": "active"}}, {"total_battles": 9, "entered_battles": 9, "player": "eugene1", "join_date": "2022-09-18T09:37:12.000Z", "wins": 4, "losses": 5, "draws": 0, "finish": 84, "meta_pts": 78, "meta_pts_float": 2200, "defeated": "h0rcs0g,mad-runner,keeegs,elbrava", "fray_index": 9, "brawl_level": 3, "player_data": {"player": "eugene1", "rating": 2824, "avatar_id": 0, "title_pre": null, "title_post": null, "display_name": null, "league": 3, "modern_league": 1, "collection_power": 7600, "starter_pack_purchase": true, "guild_id": "1e606081b97e373b9af4480704f0a4dd0c97efb7", "guild_rank": 3, "guild_join_date": "2022-02-22T15:13:48.000Z", "guild_status": "active"}}, {"total_battles": 7, "entered_battles": 7, "player": "hemihemi", "join_date": "2022-09-17T06:40:09.000Z", "wins": 3, "losses": 4, "draws": 0, "finish": 94, "meta_pts": 36, "meta_pts_float": 300, "defeated": "orthrod,tabzdagreat101,mdevastatorx", "fray_index": 13, "brawl_level": 3, "player_data": {"player": "hemihemi", "rating": 0, "avatar_id": 0, "title_pre": null, "title_post": null, "display_name": null, "league": 0, "modern_league": 0, "collection_power": 0, "starter_pack_purchase": true, "guild_id": null, "guild_rank": null, "guild_join_date": null, "guild_status": null}}, {"total_battles": 9, "entered_battles": 9, "player": "hawaii12", "join_date": "2022-09-17T01:53:48.000Z", "wins": 3, "losses": 6, "draws": 0, "finish": 102, "meta_pts": 78, "meta_pts_float": 1200, "defeated": "frombehind,su4rt,baclali", "fray_index": 4, "brawl_level": 3, "player_data": {"player": "hawaii12", "rating": 1649, "avatar_id": 16, "title_pre": null, "title_post": null, "display_name": null, "league": 6, "modern_league": 0, "collection_power": 145140, "starter_pack_purchase": true, "guild_id": "1e606081b97e373b9af4480704f0a4dd0c97efb7", "guild_rank": 1, "guild_join_date": "2022-08-09T20:30:12.000Z", "guild_status": "active"}}, {"total_battles": 9, "entered_battles": 9, "player": "seattlea", "join_date": "2022-09-17T00:45:00.000Z", "wins": 3, "losses": 6, "draws": 0, "finish": 107, "meta_pts": 60, "meta_pts_float": 0, "defeated": "lelouch21,marko499,john-chen", "fray_index": 5, "brawl_level": 3, "player_data": {"player": "seattlea", "rating": 0, "avatar_id": 0, "title_pre": null, "title_post": null, "display_name": null, "league": 0, "modern_league": 0, "collection_power": 154390, "starter_pack_purchase": true, "guild_id": "1e606081b97e373b9af4480704f0a4dd0c97efb7", "guild_rank": 4, "guild_join_date": "2022-08-22T15:58:39.000Z", "guild_status": "active"}}, {"total_battles": 9, "entered_battles": 9, "player": "neophyte142068", "join_date": "2022-09-17T06:39:39.000Z", "wins": 3, "losses": 6, "draws": 0, "finish": 110, "meta_pts": 54, "meta_pts_float": 900, "defeated": "occhiblu,ibu1987,real-mad-mac", "fray_index": 3, "brawl_level": 3, "player_data": {"player": "neophyte142068", "rating": 2739, "avatar_id": 6, "title_pre": null, "title_post": null, "display_name": null, "league": 8, "modern_league": 6, "collection_power": 174669, "starter_pack_purchase": true, "guild_id": "1e606081b97e373b9af4480704f0a4dd0c97efb7", "guild_rank": 4, "guild_join_date": "2021-09-25T01:55:54.000Z", "guild_status": "active"}}, {"total_battles": 9, "entered_battles": 9, "player": "dynamicrypto", "join_date": "2022-09-18T04:20:39.000Z", "wins": 2, "losses": 7, "draws": 0, "finish": 129, "meta_pts": 48, "meta_pts_float": 0, "defeated": "daveirah,danny52", "fray_index": 2, "brawl_level": 3, "player_data": {"player": "dynamicrypto", "rating": 0, "avatar_id": 9, "title_pre": null, "title_post": null, "display_name": null, "league": 0, "modern_league": 0, "collection_power": 13910, "starter_pack_purchase": true, "guild_id": "1e606081b97e373b9af4480704f0a4dd0c97efb7", "guild_rank": 5, "guild_join_date": "2021-09-24T03:51:00.000Z", "guild_status": "active"}}, {"total_battles": 9, "entered_battles": 9, "player": "serge100", "join_date": "2022-09-17T08:30:18.000Z", "wins": 1, "losses": 8, "draws": 0, "finish": 138, "meta_pts": 36, "meta_pts_float": 900, "defeated": "cmplxty", "fray_index": 10, "brawl_level": 3, "player_data": {"player": "serge100", "rating": 0, "avatar_id": 0, "title_pre": null, "title_post": null, "display_name": null, "league": 0, "modern_league": 10, "collection_power": 302698, "starter_pack_purchase": true, "guild_id": "1e606081b97e373b9af4480704f0a4dd0c97efb7", "guild_rank": 4, "guild_join_date": "2021-10-01T19:02:00.000Z", "guild_status": "active"}}], "guilds": [{"id": "94818cc66694e83dadf5f63b221f1653f828c52f", "name": "ZZ9PZA", "data": "{\"crest\":{\"banner\":\"blue\",\"decal\":\"book\"}}", "total_payout": 66, "cycle": 107, "wins": 73, "losses": 55, "draws": 0, "pts": 219, "top_payout": 24, "other_payout": 42, "brawl_level": 4, "guild_rank": 33, "total_merits_payout": 66000, "member_merits_payout": 4125, "total_sps_payout": "0.000", "member_sps_payout": "0.000"}, {"id": "4d379b1725b8ca17bc9a29d40bfe60735a7c1222", "name": "Immortal Gods 6", "data": "{\"crest\":{\"banner\":\"black\",\"decal\":\"sword\"}}", "total_payout": 57, "cycle": 107, "wins": 72, "losses": 41, "draws": 0, "pts": 216, "top_payout": 16, "other_payout": 41, "brawl_level": 4, "guild_rank": 112, "total_merits_payout": 41678, "member_merits_payout": 3206, "total_sps_payout": "0.000", "member_sps_payout": "0.000"}, {"id": "62a375d44acd2ff4f19739e2d7ff82ab6ccd597a", "name": "Immortal Gods 5", "data": "{\"crest\":{\"banner\":\"black\",\"decal\":\"sword\"}}", "total_payout": 49, "cycle": 107, "wins": 71, "losses": 57, "draws": 0, "pts": 213, "top_payout": 8, "other_payout": 41, "brawl_level": 4, "guild_rank": 107, "total_merits_payout": 44096, "member_merits_payout": 2756, "total_sps_payout": "0.000", "member_sps_payout": "0.000"}, {"id": "b5104f7a4ac1b26a8521bf67dac3b47c0d99d2db", "name": "Digitspin FuriousChickens", "data": "{\"crest\":{\"banner\":\"yellow\",\"decal\":\"bolt\"}}", "total_payout": 40, "cycle": 107, "wins": 70, "losses": 58, "draws": 0, "pts": 210, "top_payout": 0, "other_payout": 40, "brawl_level": 4, "guild_rank": 76, "total_merits_payout": 40000, "member_merits_payout": 2500, "total_sps_payout": "0.000", "member_sps_payout": "0.000"}, {"id": "c85f07e6659ad1489ff86a2f2474bad81022b763", "name": "Blue Pill Society", "data": "{\"crest\":{\"banner\":\"blue\",\"decal\":\"hand\"}}", "total_payout": 37, "cycle": 107, "wins": 64, "losses": 57, "draws": 0, "pts": 192, "top_payout": 0, "other_payout": 37, "brawl_level": 4, "guild_rank": 202, "total_merits_payout": 29134, "member_merits_payout": 2081, "total_sps_payout": "0.000", "member_sps_payout": "0.000"}, {"id": "1e606081b97e373b9af4480704f0a4dd0c97efb7", "name": "THGaming Brawlers", "data": "{\"crest\":{\"banner\":\"green\",\"decal\":\"hand\"}}", "total_payout": 35, "cycle": 107, "wins": 61, "losses": 60, "draws": 0, "pts": 183, "top_payout": 0, "other_payout": 35, "brawl_level": 3, "guild_rank": 176, "total_merits_payout": 26910, "member_merits_payout": 1969, "total_sps_payout": "0.000", "member_sps_payout": "0.000"}, {"id": "76ccf736f7e8939dfb9e893c3eb53035481eaa2b", "name": "6KWORKWEEK", "data": "{\"crest\":{\"banner\":\"red\",\"decal\":\"hand\"}}", "total_payout": 33, "cycle": 107, "wins": 57, "losses": 71, "draws": 0, "pts": 171, "top_payout": 0, "other_payout": 33, "brawl_level": 4, "guild_rank": 125, "total_merits_payout": 23833, "member_merits_payout": 1650, "total_sps_payout": "0.000", "member_sps_payout": "0.000"}, {"id": "8c2c80af29bfa09b266643cb5140953be69c3567", "name": "Phoenix Uraenus (\u203f!\u203f) ", "data": "{\"crest\":{\"banner\":\"purple\",\"decal\":\"staff\"}}", "total_payout": 27, "cycle": 107, "wins": 47, "losses": 62, "draws": 0, "pts": 141, "top_payout": 0, "other_payout": 27, "brawl_level": 3, "guild_rank": 168, "total_merits_payout": 17550, "member_merits_payout": 1350, "total_sps_payout": "0.000", "member_sps_payout": "0.000"}, {"id": "969c06744e81863dd5c8c923e1cdd0ed0726ff49", "name": "SoulReapers", "data": "{\"crest\":{\"banner\":\"black\",\"decal\":\"helm\"}}", "total_payout": 26, "cycle": 107, "wins": 46, "losses": 68, "draws": 0, "pts": 138, "top_payout": 0, "other_payout": 26, "brawl_level": 3, "guild_rank": 115, "total_merits_payout": 15600, "member_merits_payout": 1300, "total_sps_payout": "0.000", "member_sps_payout": "0.000"}, {"id": "b474a69eb936609e1bb4de38fd68038a59ee0e07", "name": "EDSF", "data": "{\"crest\":{\"banner\":\"blue\",\"decal\":\"axe\"}}", "total_payout": 22, "cycle": 107, "wins": 40, "losses": 74, "draws": 0, "pts": 120, "top_payout": 0, "other_payout": 22, "brawl_level": 3, "guild_rank": 344, "total_merits_payout": 12506, "member_merits_payout": 962, "total_sps_payout": "0.000", "member_sps_payout": "0.000"}]}