{"id": "GUILD-BC95-BL12-BRAWL1", "format": "swiss", "sub_format": "brawl", "start_date": "2022-07-16T12:00:00.000Z", "status": 2, "data": {"duration_blocks": 57600, "multiple_rounds": false, "cp_min": 0, "spsp_min": 0, "group_size": 10, "create_team_seconds": 168, "challenge_level": 0, "guilds": ["500ec675489cdb7430b16c639aa08c039a70f650", "5310a34e3d99fd5c80b1447b42ec32973fee71d0", "677570c96cd24e7de1a0300973ec1002036113bf", "e2bdb0b670c99f75ba7001dc667a7a01ea1e4758", "32aff7dc4eb79a1a884d734ea1f38065e0b1c435", "15689b96aa00e3752d7018b7fc4e444202683f5c", "8aa9c0ce5ea7bf8bfe45b9e6fa3a342aa9f67c44", "730923bb5fbdf5c83e1fe7e21be3662e73589150", "92d554b52fedc88e992ef82bb763b59d1ad02b33", "9121f2c83b38a2d08228785e7b86ffe723a70386"], "crown_pot": 116}, "players": [{"total_battles": 8, "entered_battles": 8, "player": "lunchboxxx", "join_date": "2022-07-15T02:49:27.000Z", "wins": 7, "losses": 1, "draws": 0, "finish": 6, "meta_pts": 124, "meta_pts_float": 2103, "defeated": "jonny2toes,mimik-aud,vb-kevin,vagabond42069,macnapat7,nowhereman630,magdalena1b", "fray_index": 1, "brawl_level": 2, "player_data": {"player": "lunchboxxx", "rating": 0, "avatar_id": 20, "title_pre": null, "title_post": null, "display_name": null, "league": 0, "modern_league": 0, "collection_power": 131845, "starter_pack_purchase": true, "guild_id": "730923bb5fbdf5c83e1fe7e21be3662e73589150", "guild_rank": 2, "guild_join_date": "2022-05-12T19:52:30.000Z", "guild_status": "active"}}, {"total_battles": 6, "entered_battles": 6, "player": "nifbarb", "join_date": "2022-07-15T12:06:42.000Z", "wins": 6, "losses": 0, "draws": 0, "finish": 8, "meta_pts": 90, "meta_pts_float": 3568, "defeated": "plicc8,evilrukus,ggbouncy,roar25,lyrya,macnapat4", "fray_index": 9, "brawl_level": 2, "player_data": {"player": "nifbarb", "rating": 2800, "avatar_id": 15, "title_pre": null, "title_post": null, "display_name": null, "league": 10, "modern_league": 9, "collection_power": 1195352, "starter_pack_purchase": true, "guild_id": "730923bb5fbdf5c83e1fe7e21be3662e73589150", "guild_rank": 3, "guild_join_date": "2022-03-15T06:55:51.000Z", "guild_status": "active"}}, {"total_battles": 7, "entered_battles": 7, "player": "cenira", "join_date": "2022-07-14T12:02:12.000Z", "wins": 6, "losses": 1, "draws": 0, "finish": 9, "meta_pts": 114, "meta_pts_float": 2019, "defeated": "riciuz,macnapat9,beatricebex,benry,corylus,sahrotaar", "fray_index": 2, "brawl_level": 2, "player_data": {"player": "cenira", "rating": 1600, "avatar_id": 12, "title_pre": null, "title_post": null, "display_name": null, "league": 6, "modern_league": 8, "collection_power": 302211, "starter_pack_purchase": true, "guild_id": "730923bb5fbdf5c83e1fe7e21be3662e73589150", "guild_rank": 2, "guild_join_date": "2021-12-18T08:17:12.000Z", "guild_status": "active"}}, {"total_battles": 7, "entered_battles": 7, "player": "z3ll", "join_date": "2022-07-14T16:25:39.000Z", "wins": 6, "losses": 1, "draws": 0, "finish": 10, "meta_pts": 84, "meta_pts_float": 2633, "defeated": "genepoolupstart,diogenes32,macnapat2,mappis,paine17,turboturtle", "fray_index": 8, "brawl_level": 2, "player_data": {"player": "z3ll", "rating": 2467, "avatar_id": 0, "title_pre": null, "title_post": null, "display_name": null, "league": 8, "modern_league": 0, "collection_power": 370305, "starter_pack_purchase": true, "guild_id": "730923bb5fbdf5c83e1fe7e21be3662e73589150", "guild_rank": 3, "guild_join_date": "2021-12-25T02:38:36.000Z", "guild_status": "active"}}, {"total_battles": 8, "entered_battles": 8, "player": "timtone", "join_date": "2022-07-14T16:21:42.000Z", "wins": 6, "losses": 2, "draws": 0, "finish": 12, "meta_pts": 96, "meta_pts_float": 1915, "defeated": "cptneckfat,pkdorn,macnapat5,aizsa,coltello,souschef42", "fray_index": 0, "brawl_level": 2, "player_data": {"player": "timtone", "rating": 0, "avatar_id": 9, "title_pre": null, "title_post": null, "display_name": null, "league": 0, "modern_league": 8, "collection_power": 75050, "starter_pack_purchase": true, "guild_id": "730923bb5fbdf5c83e1fe7e21be3662e73589150", "guild_rank": 2, "guild_join_date": "2022-07-13T01:06:45.000Z", "guild_status": "active"}}, {"total_battles": 5, "entered_battles": 5, "player": "hungryfortacos", "join_date": "2022-07-14T20:14:09.000Z", "wins": 5, "losses": 0, "draws": 0, "finish": 13, "meta_pts": 60, "meta_pts_float": 2800, "defeated": "dubble.eth,sinpsy,eyen,vash7575,vazbeast", "fray_index": 3, "brawl_level": 2, "player_data": {"player": "hungryfortacos", "rating": 2200, "avatar_id": 0, "title_pre": null, "title_post": null, "display_name": null, "league": 8, "modern_league": 9, "collection_power": 769821, "starter_pack_purchase": true, "guild_id": "730923bb5fbdf5c83e1fe7e21be3662e73589150", "guild_rank": 3, "guild_join_date": "2021-12-11T20:23:54.000Z", "guild_status": "active"}}, {"total_battles": 7, "entered_battles": 7, "player": "bl4nkk", "join_date": "2022-07-15T03:35:21.000Z", "wins": 5, "losses": 2, "draws": 0, "finish": 20, "meta_pts": 66, "meta_pts_float": 100, "defeated": "elusivemayhem,frsh.bnthg,vaznft,macnapat8,engenheiro", "fray_index": 5, "brawl_level": 2, "player_data": {"player": "bl4nkk", "rating": 20, "avatar_id": 0, "title_pre": null, "title_post": null, "display_name": null, "league": 0, "modern_league": 0, "collection_power": 14480, "starter_pack_purchase": true, "guild_id": null, "guild_rank": null, "guild_join_date": null, "guild_status": null}}, {"total_battles": 8, "entered_battles": 8, "player": "daljalon", "join_date": "2022-07-14T17:46:39.000Z", "wins": 5, "losses": 3, "draws": 0, "finish": 22, "meta_pts": 102, "meta_pts_float": 2840, "defeated": "mydnyt-shadow,demmio,kaatojon,macnapat1,npieken", "fray_index": 7, "brawl_level": 2, "player_data": {"player": "daljalon", "rating": 2407, "avatar_id": 1, "title_pre": null, "title_post": "The Gambler", "display_name": null, "league": 8, "modern_league": 1, "collection_power": 1307298, "starter_pack_purchase": true, "guild_id": "730923bb5fbdf5c83e1fe7e21be3662e73589150", "guild_rank": 3, "guild_join_date": "2022-03-15T12:50:30.000Z", "guild_status": "active"}}, {"total_battles": 5, "entered_battles": 5, "player": "rebelyell666", "join_date": "2022-07-15T13:35:09.000Z", "wins": 4, "losses": 1, "draws": 0, "finish": 26, "meta_pts": 38, "meta_pts_float": 2447, "defeated": "un-leash,omgodist,phoenix-bank,sinpsyc05", "fray_index": 11, "brawl_level": 2, "player_data": {"player": "rebelyell666", "rating": 2878, "avatar_id": 6, "title_pre": null, "title_post": null, "display_name": null, "league": 10, "modern_league": 10, "collection_power": 890451, "starter_pack_purchase": true, "guild_id": "730923bb5fbdf5c83e1fe7e21be3662e73589150", "guild_rank": 2, "guild_join_date": "2022-02-04T18:18:00.000Z", "guild_status": "active"}}, {"total_battles": 6, "entered_battles": 6, "player": "pathfinderchris", "join_date": "2022-07-14T17:31:48.000Z", "wins": 4, "losses": 2, "draws": 0, "finish": 28, "meta_pts": 66, "meta_pts_float": 1786, "defeated": "lilcart5,larinda,frepp,whitenose", "fray_index": 6, "brawl_level": 2, "player_data": {"player": "pathfinderchris", "rating": 0, "avatar_id": 15, "title_pre": null, "title_post": null, "display_name": null, "league": 0, "modern_league": 7, "collection_power": 186365, "starter_pack_purchase": true, "guild_id": "730923bb5fbdf5c83e1fe7e21be3662e73589150", "guild_rank": 2, "guild_join_date": "2022-02-16T03:24:15.000Z", "guild_status": "active"}}, {"total_battles": 7, "entered_battles": 7, "player": "iceman99", "join_date": "2022-07-14T13:29:06.000Z", "wins": 4, "losses": 3, "draws": 0, "finish": 37, "meta_pts": 50, "meta_pts_float": 2177, "defeated": "naponson,trailblazers99,macnapat,engilhramn", "fray_index": 4, "brawl_level": 2, "player_data": {"player": "iceman99", "rating": 2445, "avatar_id": 0, "title_pre": null, "title_post": null, "display_name": null, "league": 8, "modern_league": 0, "collection_power": 196445, "starter_pack_purchase": true, "guild_id": "730923bb5fbdf5c83e1fe7e21be3662e73589150", "guild_rank": 2, "guild_join_date": "2022-02-15T03:31:27.000Z", "guild_status": "active"}}, {"total_battles": 6, "entered_battles": 6, "player": "marandis", "join_date": "2022-07-15T07:40:03.000Z", "wins": 3, "losses": 3, "draws": 0, "finish": 57, "meta_pts": 30, "meta_pts_float": 3100, "defeated": "huyquangvtvn1,chiboulette2,vazthink", "fray_index": 12, "brawl_level": 2, "player_data": {"player": "marandis", "rating": 2057, "avatar_id": 0, "title_pre": null, "title_post": null, "display_name": null, "league": 7, "modern_league": 7, "collection_power": 430117, "starter_pack_purchase": true, "guild_id": "730923bb5fbdf5c83e1fe7e21be3662e73589150", "guild_rank": 2, "guild_join_date": "2022-06-03T06:27:57.000Z", "guild_status": "active"}}, {"total_battles": 5, "entered_battles": 5, "player": "fluidflame", "join_date": "2022-07-14T16:49:06.000Z", "wins": 1, "losses": 4, "draws": 0, "finish": 81, "meta_pts": 0, "meta_pts_float": 3100, "defeated": "macnapat10", "fray_index": 10, "brawl_level": 2, "player_data": {"player": "fluidflame", "rating": 2500, "avatar_id": 6, "title_pre": null, "title_post": "The Legionnaire", "display_name": null, "league": 9, "modern_league": 12, "collection_power": 617975, "starter_pack_purchase": true, "guild_id": "730923bb5fbdf5c83e1fe7e21be3662e73589150", "guild_rank": 5, "guild_join_date": "2021-12-05T19:13:27.000Z", "guild_status": "active"}}], "guilds": [{"id": "730923bb5fbdf5c83e1fe7e21be3662e73589150", "name": "[YGG] Legion", "data": "{\"crest\":{\"banner\":\"black\",\"decal\":\"skull\"}}", "total_payout": 27, "cycle": 95, "wins": 62, "losses": 23, "draws": 0, "pts": 186, "top_payout": 7, "other_payout": 20, "brawl_level": 2, "guild_rank": 125, "total_merits_payout": 21606, "member_merits_payout": 1662, "total_sps_payout": "0.000", "member_sps_payout": "0.000"}, {"id": "92d554b52fedc88e992ef82bb763b59d1ad02b33", "name": "Primate Prospectors", "data": "{\"crest\":{\"banner\":\"pink\",\"decal\":\"wolf\"}}", "total_payout": 22, "cycle": 95, "wins": 55, "losses": 28, "draws": 1, "pts": 166, "top_payout": 5, "other_payout": 17, "brawl_level": 2, "guild_rank": 227, "total_merits_payout": 15405, "member_merits_payout": 1185, "total_sps_payout": "0.000", "member_sps_payout": "0.000"}, {"id": "32aff7dc4eb79a1a884d734ea1f38065e0b1c435", "name": "Crypto Rats", "data": "{\"crest\":{\"banner\":\"black\",\"decal\":\"axe\"}}", "total_payout": 16, "cycle": 95, "wins": 45, "losses": 35, "draws": 0, "pts": 135, "top_payout": 2, "other_payout": 14, "brawl_level": 2, "guild_rank": 211, "total_merits_payout": 9482, "member_merits_payout": 862, "total_sps_payout": "0.000", "member_sps_payout": "0.000"}, {"id": "9121f2c83b38a2d08228785e7b86ffe723a70386", "name": "Phoenix Hatchlings", "data": "{\"crest\":{\"banner\":\"pink\",\"decal\":\"book\"}}", "total_payout": 11, "cycle": 95, "wins": 35, "losses": 48, "draws": 2, "pts": 107, "top_payout": 0, "other_payout": 11, "brawl_level": 1, "guild_rank": 388, "total_merits_payout": 5080, "member_merits_payout": 508, "total_sps_payout": "0.000", "member_sps_payout": "0.000"}, {"id": "8aa9c0ce5ea7bf8bfe45b9e6fa3a342aa9f67c44", "name": "PsyChEcu", "data": "{\"crest\":{\"banner\":\"red\",\"decal\":\"skull\"}}", "total_payout": 10, "cycle": 95, "wins": 31, "losses": 53, "draws": 0, "pts": 93, "top_payout": 0, "other_payout": 10, "brawl_level": 1, "guild_rank": 151, "total_merits_payout": 5005, "member_merits_payout": 385, "total_sps_payout": "0.000", "member_sps_payout": "0.000"}, {"id": "e2bdb0b670c99f75ba7001dc667a7a01ea1e4758", "name": "Helpie-Caster Pizza Crew ", "data": "{\"crest\":{\"banner\":\"red\",\"decal\":\"bolt\"}}", "total_payout": 9, "cycle": 95, "wins": 29, "losses": 32, "draws": 2, "pts": 89, "top_payout": 0, "other_payout": 9, "brawl_level": 2, "guild_rank": 493, "total_merits_payout": 3880, "member_merits_payout": 485, "total_sps_payout": "0.000", "member_sps_payout": "0.000"}, {"id": "677570c96cd24e7de1a0300973ec1002036113bf", "name": "Mega Therion", "data": "{\"crest\":{\"banner\":\"green\",\"decal\":\"wolf\"}}", "total_payout": 9, "cycle": 95, "wins": 28, "losses": 43, "draws": 0, "pts": 84, "top_payout": 0, "other_payout": 9, "brawl_level": 2, "guild_rank": 279, "total_merits_payout": 4565, "member_merits_payout": 415, "total_sps_payout": "0.000", "member_sps_payout": "0.000"}, {"id": "500ec675489cdb7430b16c639aa08c039a70f650", "name": "YGG Brawlers (Midgard)", "data": "{\"crest\":{\"banner\":\"yellow\",\"decal\":\"bolt\"}}", "total_payout": 8, "cycle": 95, "wins": 25, "losses": 39, "draws": 0, "pts": 75, "top_payout": 0, "other_payout": 8, "brawl_level": 1, "guild_rank": 555, "total_merits_payout": 2452, "member_merits_payout": 369, "total_sps_payout": "0.000", "member_sps_payout": "0.000"}, {"id": "15689b96aa00e3752d7018b7fc4e444202683f5c", "name": "2NL | 2 NEXT LIFE", "data": "{\"crest\":{\"banner\":\"silver\",\"decal\":\"tree\"}}", "total_payout": 2, "cycle": 95, "wins": 7, "losses": 9, "draws": 0, "pts": 21, "top_payout": 0, "other_payout": 2, "brawl_level": 1, "guild_rank": 763, "total_merits_payout": 92, "member_merits_payout": 92, "total_sps_payout": "0.000", "member_sps_payout": "0.000"}, {"id": "5310a34e3d99fd5c80b1447b42ec32973fee71d0", "name": "EldenSquad", "data": "{\"crest\":{\"banner\":\"black\",\"decal\":\"bolt\"}}", "total_payout": 2, "cycle": 95, "wins": 5, "losses": 16, "draws": 1, "pts": 16, "top_payout": 0, "other_payout": 2, "brawl_level": 1, "guild_rank": 1017, "total_merits_payout": 116, "member_merits_payout": 77, "total_sps_payout": "0.000", "member_sps_payout": "0.000"}]}