{"id": "GUILD-BC107-BL12-BRAWL21", "format": "swiss", "sub_format": "brawl", "start_date": "2022-09-19T00:40:00.000Z", "status": 2, "data": {"duration_blocks": 57600, "multiple_rounds": false, "cp_min": 0, "spsp_min": 0, "group_size": 10, "create_team_seconds": 168, "challenge_level": 0, "guilds": ["b8c67a91e2fa5a04554998de919b24c07ea6bf55", "dce5d707bbbf8899322fa6b5418645d4cf21efa9", "8fc2f2de3636cf2af39fd071eb4a9378f1fc8eee", "767d2a48b292852339483453b0f5f46b9b338491", "af31e06366f3ba86275ca90ec9e5727d66e92249", "5791b7c053b11f571a897aba86cbc912ccf61126", "8aea781d645ca82aef1bc0b1ec754bba78003e9d", "8a3b9b68eb6c83987d9ac451b0efb751f57f1c3c", "b29db708b72d19343e3a64638b0a290809a4a0e4", "8adfebf54b6b29090d4f2d91d53ca0ce3b93247f"], "crown_pot": 64}, "players": [{"total_battles": 9, "entered_battles": 9, "player": "sevenharbs", "join_date": "2022-09-18T11:29:36.000Z", "wins": 9, "losses": 0, "draws": 0, "finish": 1, "meta_pts": 180, "meta_pts_float": 1977, "defeated": "itachiuchiha94,yumeejeen,ganymede415,luckyghreat88,deus-x-machina,pagsy41,adoyskie,darkne33,bonkichi", "fray_index": 0, "brawl_level": 2, "player_data": {"player": "sevenharbs", "rating": 2692, "avatar_id": 8, "title_pre": null, "title_post": null, "display_name": null, "league": 9, "modern_league": 9, "collection_power": 339175, "starter_pack_purchase": true, "guild_id": "767d2a48b292852339483453b0f5f46b9b338491", "guild_rank": 1, "guild_join_date": "2022-04-06T09:15:36.000Z", "guild_status": "active"}}, {"total_battles": 7, "entered_battles": 7, "player": "chaen", "join_date": "2022-09-18T01:10:57.000Z", "wins": 7, "losses": 0, "draws": 0, "finish": 3, "meta_pts": 90, "meta_pts_float": 1307, "defeated": "hayashimasao,bilcock,higeneko,thienphucgaucon,idiwow,jadeite,popols", "fray_index": 2, "brawl_level": 2, "player_data": {"player": "chaen", "rating": 1899, "avatar_id": 12, "title_pre": null, "title_post": null, "display_name": null, "league": 6, "modern_league": 8, "collection_power": 119040, "starter_pack_purchase": true, "guild_id": "767d2a48b292852339483453b0f5f46b9b338491", "guild_rank": 1, "guild_join_date": "2022-05-10T15:16:51.000Z", "guild_status": "active"}}, {"total_battles": 6, "entered_battles": 6, "player": "osum", "join_date": "2022-09-18T11:59:27.000Z", "wins": 6, "losses": 0, "draws": 0, "finish": 5, "meta_pts": 72, "meta_pts_float": 117, "defeated": "dsky55,cloudjoseph,michlo,mysteryarrow84,xiv777,snoopgoat", "fray_index": 1, "brawl_level": 2, "player_data": {"player": "osum", "rating": 128, "avatar_id": 5, "title_pre": null, "title_post": null, "display_name": null, "league": 1, "modern_league": 8, "collection_power": 159390, "starter_pack_purchase": true, "guild_id": "767d2a48b292852339483453b0f5f46b9b338491", "guild_rank": 1, "guild_join_date": "2022-01-23T04:43:27.000Z", "guild_status": "active"}}, {"total_battles": 4, "entered_battles": 4, "player": "zuyukk77", "join_date": "2022-09-18T05:11:30.000Z", "wins": 4, "losses": 0, "draws": 0, "finish": 16, "meta_pts": 36, "meta_pts_float": 1314, "defeated": "xman9916,contesmn,axemaster55,taraki", "fray_index": 6, "brawl_level": 2, "player_data": {"player": "zuyukk77", "rating": 100, "avatar_id": 20, "title_pre": null, "title_post": null, "display_name": null, "league": 1, "modern_league": 5, "collection_power": 138535, "starter_pack_purchase": true, "guild_id": "767d2a48b292852339483453b0f5f46b9b338491", "guild_rank": 1, "guild_join_date": "2022-01-10T14:14:09.000Z", "guild_status": "active"}}, {"total_battles": 4, "entered_battles": 4, "player": "octopusko", "join_date": "2022-09-18T01:16:54.000Z", "wins": 4, "losses": 0, "draws": 0, "finish": 18, "meta_pts": 18, "meta_pts_float": 0, "defeated": "shocker555,jir,daryll24,idiwow4", "fray_index": 10, "brawl_level": 2, "player_data": {"player": "octopusko", "rating": 0, "avatar_id": 16, "title_pre": null, "title_post": null, "display_name": null, "league": 0, "modern_league": 6, "collection_power": 82625, "starter_pack_purchase": true, "guild_id": "767d2a48b292852339483453b0f5f46b9b338491", "guild_rank": 2, "guild_join_date": "2021-08-17T23:02:51.000Z", "guild_status": "active"}}, {"total_battles": 5, "entered_battles": 5, "player": "gaoga", "join_date": "2022-09-17T06:30:51.000Z", "wins": 4, "losses": 1, "draws": 0, "finish": 19, "meta_pts": 42, "meta_pts_float": 0, "defeated": "joe-average,dnomad88,mdasein,tak0yakyy", "fray_index": 7, "brawl_level": 2, "player_data": {"player": "gaoga", "rating": 0, "avatar_id": 12, "title_pre": null, "title_post": null, "display_name": null, "league": 0, "modern_league": 7, "collection_power": 119865, "starter_pack_purchase": true, "guild_id": "767d2a48b292852339483453b0f5f46b9b338491", "guild_rank": 4, "guild_join_date": "2021-07-28T14:32:15.000Z", "guild_status": "active"}}, {"total_battles": 3, "entered_battles": 3, "player": "marimo4", "join_date": "2022-09-17T21:46:12.000Z", "wins": 3, "losses": 0, "draws": 0, "finish": 23, "meta_pts": 18, "meta_pts_float": 1592, "defeated": "daniel-wng,archninja,mhar01", "fray_index": 12, "brawl_level": 2, "player_data": {"player": "marimo4", "rating": 2303, "avatar_id": 0, "title_pre": null, "title_post": null, "display_name": null, "league": 8, "modern_league": 0, "collection_power": 222565, "starter_pack_purchase": true, "guild_id": "767d2a48b292852339483453b0f5f46b9b338491", "guild_rank": 5, "guild_join_date": "2021-07-28T00:16:33.000Z", "guild_status": "active"}}, {"total_battles": 3, "entered_battles": 3, "player": "pitannnosuko", "join_date": "2022-09-17T13:36:18.000Z", "wins": 3, "losses": 0, "draws": 0, "finish": 24, "meta_pts": 18, "meta_pts_float": 672, "defeated": "gringo94,jiruno,idiwow3", "fray_index": 11, "brawl_level": 2, "player_data": {"player": "pitannnosuko", "rating": 0, "avatar_id": 1, "title_pre": null, "title_post": null, "display_name": null, "league": 0, "modern_league": 5, "collection_power": 188035, "starter_pack_purchase": true, "guild_id": "767d2a48b292852339483453b0f5f46b9b338491", "guild_rank": 3, "guild_join_date": "2021-08-14T01:09:39.000Z", "guild_status": "active"}}, {"total_battles": 4, "entered_battles": 4, "player": "cryptoee", "join_date": "2022-09-17T10:10:18.000Z", "wins": 3, "losses": 1, "draws": 0, "finish": 28, "meta_pts": 24, "meta_pts_float": 1478, "defeated": "dsky02,gadred25,marinmex", "fray_index": 5, "brawl_level": 2, "player_data": {"player": "cryptoee", "rating": 2249, "avatar_id": 9, "title_pre": null, "title_post": null, "display_name": null, "league": 7, "modern_league": 0, "collection_power": 143200, "starter_pack_purchase": true, "guild_id": "767d2a48b292852339483453b0f5f46b9b338491", "guild_rank": 3, "guild_join_date": "2021-07-28T01:06:03.000Z", "guild_status": "active"}}, {"total_battles": 4, "entered_battles": 4, "player": "sakurakoko", "join_date": "2022-09-18T09:29:27.000Z", "wins": 3, "losses": 1, "draws": 0, "finish": 32, "meta_pts": 0, "meta_pts_float": 0, "defeated": "toast88,softdrink102,idiwow2", "fray_index": 3, "brawl_level": 2, "player_data": {"player": "sakurakoko", "rating": 0, "avatar_id": 0, "title_pre": null, "title_post": null, "display_name": null, "league": 0, "modern_league": 3, "collection_power": 37060, "starter_pack_purchase": true, "guild_id": "767d2a48b292852339483453b0f5f46b9b338491", "guild_rank": 2, "guild_join_date": "2021-12-15T22:41:18.000Z", "guild_status": "active"}}, {"total_battles": 4, "entered_battles": 4, "player": "macha-tw", "join_date": "2022-09-17T03:27:48.000Z", "wins": 2, "losses": 2, "draws": 0, "finish": 44, "meta_pts": 12, "meta_pts_float": 1600, "defeated": "merlie,jaynuts", "fray_index": 8, "brawl_level": 2, "player_data": {"player": "macha-tw", "rating": 1279, "avatar_id": 20, "title_pre": null, "title_post": null, "display_name": null, "league": 4, "modern_league": 9, "collection_power": 242200, "starter_pack_purchase": true, "guild_id": "767d2a48b292852339483453b0f5f46b9b338491", "guild_rank": 2, "guild_join_date": "2021-10-24T03:08:36.000Z", "guild_status": "active"}}, {"total_battles": 4, "entered_battles": 4, "player": "tarachan64", "join_date": "2022-09-18T11:24:27.000Z", "wins": 1, "losses": 3, "draws": 0, "finish": 51, "meta_pts": 0, "meta_pts_float": 752, "defeated": "idiwow1", "fray_index": 9, "brawl_level": 2, "player_data": {"player": "tarachan64", "rating": 0, "avatar_id": 18, "title_pre": null, "title_post": null, "display_name": null, "league": 0, "modern_league": 7, "collection_power": 61200, "starter_pack_purchase": true, "guild_id": "767d2a48b292852339483453b0f5f46b9b338491", "guild_rank": 1, "guild_join_date": "2022-09-15T15:06:54.000Z", "guild_status": "active"}}, {"total_battles": 8, "entered_battles": 8, "player": "syobeni", "join_date": "2022-09-18T07:16:09.000Z", "wins": 0, "losses": 8, "draws": 0, "finish": 75, "meta_pts": 0, "meta_pts_float": 426, "defeated": null, "fray_index": 4, "brawl_level": 2, "player_data": {"player": "syobeni", "rating": 859, "avatar_id": 2, "title_pre": null, "title_post": null, "display_name": null, "league": 3, "modern_league": 0, "collection_power": 68955, "starter_pack_purchase": true, "guild_id": "767d2a48b292852339483453b0f5f46b9b338491", "guild_rank": 1, "guild_join_date": "2022-01-10T10:26:09.000Z", "guild_status": "active"}}], "guilds": [{"id": "767d2a48b292852339483453b0f5f46b9b338491", "name": "\u9f8d\u306e\u65c5\u56e3\u3000\u6731\u96c0\u968a", "data": "{\"crest\":{\"banner\":\"red\",\"decal\":\"wolf\"}}", "total_payout": 18, "cycle": 107, "wins": 49, "losses": 16, "draws": 0, "pts": 147, "top_payout": 4, "other_payout": 14, "brawl_level": 2, "guild_rank": 170, "total_merits_payout": 14952, "member_merits_payout": 1246, "total_sps_payout": "0.000", "member_sps_payout": "0.000"}, {"id": "8aea781d645ca82aef1bc0b1ec754bba78003e9d", "name": "Supernatural", "data": "{\"crest\":{\"banner\":\"black\",\"decal\":\"skull\"}}", "total_payout": 13, "cycle": 107, "wins": 34, "losses": 23, "draws": 0, "pts": 102, "top_payout": 3, "other_payout": 10, "brawl_level": 1, "guild_rank": 278, "total_merits_payout": 6000, "member_merits_payout": 600, "total_sps_payout": "0.000", "member_sps_payout": "0.000"}, {"id": "5791b7c053b11f571a897aba86cbc912ccf61126", "name": "ELIGEN", "data": "{\"crest\":{\"banner\":\"green\",\"decal\":\"globe\"}}", "total_payout": 10, "cycle": 107, "wins": 31, "losses": 30, "draws": 0, "pts": 93, "top_payout": 1, "other_payout": 9, "brawl_level": 1, "guild_rank": 313, "total_merits_payout": 3593, "member_merits_payout": 385, "total_sps_payout": "0.000", "member_sps_payout": "0.000"}, {"id": "8fc2f2de3636cf2af39fd071eb4a9378f1fc8eee", "name": "D' Lanasian Phoenix", "data": "{\"crest\":{\"banner\":\"red\",\"decal\":\"shield\"}}", "total_payout": 8, "cycle": 107, "wins": 29, "losses": 36, "draws": 0, "pts": 87, "top_payout": 0, "other_payout": 8, "brawl_level": 1, "guild_rank": 632, "total_merits_payout": 2952, "member_merits_payout": 369, "total_sps_payout": "0.000", "member_sps_payout": "0.000"}, {"id": "af31e06366f3ba86275ca90ec9e5727d66e92249", "name": "Valhalla", "data": "{\"crest\":{\"banner\":\"green\",\"decal\":\"axe\"}}", "total_payout": 7, "cycle": 107, "wins": 25, "losses": 17, "draws": 0, "pts": 75, "top_payout": 0, "other_payout": 7, "brawl_level": 2, "guild_rank": 470, "total_merits_payout": 1761, "member_merits_payout": 323, "total_sps_payout": "0.000", "member_sps_payout": "0.000"}, {"id": "b29db708b72d19343e3a64638b0a290809a4a0e4", "name": "The Hammers of Dawn", "data": "{\"crest\":{\"banner\":\"silver\",\"decal\":\"bolt\"}}", "total_payout": 4, "cycle": 107, "wins": 13, "losses": 28, "draws": 0, "pts": 39, "top_payout": 0, "other_payout": 4, "brawl_level": 1, "guild_rank": 609, "total_merits_payout": 616, "member_merits_payout": 154, "total_sps_payout": "0.000", "member_sps_payout": "0.000"}, {"id": "8adfebf54b6b29090d4f2d91d53ca0ce3b93247f", "name": "SPS Mutineers", "data": "{\"crest\":{\"banner\":\"black\",\"decal\":null}}", "total_payout": 2, "cycle": 107, "wins": 6, "losses": 11, "draws": 0, "pts": 18, "top_payout": 0, "other_payout": 2, "brawl_level": 2, "guild_rank": 955, "total_merits_payout": 92, "member_merits_payout": 92, "total_sps_payout": "0.000", "member_sps_payout": "0.000"}, {"id": "8a3b9b68eb6c83987d9ac451b0efb751f57f1c3c", "name": "orekari", "data": "{\"crest\":{\"banner\":\"black\",\"decal\":null}}", "total_payout": 1, "cycle": 107, "wins": 4, "losses": 12, "draws": 0, "pts": 12, "top_payout": 0, "other_payout": 1, "brawl_level": 1, "guild_rank": 929, "total_merits_payout": 42, "member_merits_payout": 38, "total_sps_payout": "0.000", "member_sps_payout": "0.000"}, {"id": "dce5d707bbbf8899322fa6b5418645d4cf21efa9", "name": "Stealthed Legion", "data": "{\"crest\":{\"banner\":\"purple\",\"decal\":\"skull\"}}", "total_payout": 1, "cycle": 107, "wins": 3, "losses": 29, "draws": 0, "pts": 9, "top_payout": 0, "other_payout": 1, "brawl_level": 1, "guild_rank": 707, "total_merits_payout": 38, "member_merits_payout": 38, "total_sps_payout": "0.000", "member_sps_payout": "0.000"}, {"id": "b8c67a91e2fa5a04554998de919b24c07ea6bf55", "name": "Drip.Community", "data": "{\"crest\":{\"banner\":\"purple\",\"decal\":\"hand\"}}", "total_payout": 0, "cycle": 107, "wins": 0, "losses": 38, "draws": 0, "pts": 0, "top_payout": 0, "other_payout": 0, "brawl_level": 1, "guild_rank": 808, "total_merits_payout": 0, "member_merits_payout": 0, "total_sps_payout": "0.000", "member_sps_payout": "0.000"}]}