{"id": "GUILD-BC86-BL34-BRAWL5", "format": "swiss", "sub_format": "brawl", "start_date": "2022-05-30T05:04:00.000Z", "status": 2, "data": {"duration_blocks": 57600, "multiple_rounds": false, "cp_min": 0, "spsp_min": 0, "group_size": 10, "create_team_seconds": 168, "challenge_level": 1, "guilds": ["ddb09da326f7c20d0b3714a154e8aec45208c837", "13c9cdace559afffd0ae9105f8dd9d71517093db", "02ed5efea46e5b9a0b8ef3aedb26bb31f4e59dcc", "244a02b312201b4a1cca4f8b83eec767cf8af973", "edc32f5e6e714d742463308e266165c30412c271", "f4201d176712b8adab92169c6148dc7b87509fc3", "4f97fe48fd72ff437e9df6cceacbd732e352d6cf", "60a0c13b6f13a61a424cd2a5a605ce91407709ec", "63be801ae48313632ef5dd91ddb9a815387c2c16", "30def23c7fb0958b011df5c39aedad6fd1fe34ba"], "crown_pot": 338}, "players": [{"total_battles": 8, "entered_battles": 8, "player": "szf", "join_date": "2022-05-29T09:08:51.000Z", "wins": 8, "losses": 0, "draws": 0, "finish": 2, "meta_pts": 168, "meta_pts_float": 2885, "defeated": "longdarigo,cofffeehorizon,spl-p6,bobcatg,uganzadranje,dismayedworld,alureoftheearth,sc789", "fray_index": 12, "brawl_level": 3, "player_data": {"player": "szf", "rating": 2091, "avatar_id": 14, "title_pre": null, "title_post": null, "display_name": null, "league": 7, "modern_league": 0, "collection_power": 1772345, "starter_pack_purchase": true, "guild_id": "244a02b312201b4a1cca4f8b83eec767cf8af973", "guild_rank": 5, "guild_join_date": "2019-07-30T20:26:12.000Z", "guild_status": "active"}}, {"total_battles": 9, "entered_battles": 9, "player": "simsahas", "join_date": "2022-05-29T09:08:27.000Z", "wins": 8, "losses": 1, "draws": 0, "finish": 5, "meta_pts": 180, "meta_pts_float": 4308, "defeated": "tailcock,cryptocopy,hashmask,seinkalar,vendettalts,meteoholy,devbot,aussieninja", "fray_index": 10, "brawl_level": 3, "player_data": {"player": "simsahas", "rating": 700, "avatar_id": 6, "title_pre": null, "title_post": "The Explorer", "display_name": null, "league": 3, "modern_league": 14, "collection_power": 5157530, "starter_pack_purchase": true, "guild_id": "c33e99909c5d4c219ee9ba4f62750d3f83a0bac7", "guild_rank": 4, "guild_join_date": "2022-11-07T22:00:03.000Z", "guild_status": "active"}}, {"total_battles": 7, "entered_battles": 7, "player": "raketenklaus", "join_date": "2022-05-28T16:44:57.000Z", "wins": 6, "losses": 1, "draws": 0, "finish": 20, "meta_pts": 108, "meta_pts_float": 3702, "defeated": "lordwindgrace,iieeiieeii,mann0000,peak.viking,mightpossibly,khan.dayyanz", "fray_index": 5, "brawl_level": 3, "player_data": {"player": "raketenklaus", "rating": 2800, "avatar_id": 10, "title_pre": null, "title_post": "The Legionnaire", "display_name": null, "league": 10, "modern_league": 0, "collection_power": 546373, "starter_pack_purchase": true, "guild_id": "244a02b312201b4a1cca4f8b83eec767cf8af973", "guild_rank": 3, "guild_join_date": "2021-08-05T20:10:33.000Z", "guild_status": "active"}}, {"total_battles": 8, "entered_battles": 8, "player": "maybenexttime", "join_date": "2022-05-29T16:32:15.000Z", "wins": 6, "losses": 2, "draws": 0, "finish": 26, "meta_pts": 108, "meta_pts_float": 4674, "defeated": "han2jackal,backi,lalothen,simsahas1,bji1203,meffmike", "fray_index": 14, "brawl_level": 3, "player_data": {"player": "maybenexttime", "rating": 3747, "avatar_id": 0, "title_pre": null, "title_post": "The Legionnaire", "display_name": null, "league": 13, "modern_league": 0, "collection_power": 26004776, "starter_pack_purchase": true, "guild_id": "c33e99909c5d4c219ee9ba4f62750d3f83a0bac7", "guild_rank": 4, "guild_join_date": "2022-08-05T19:56:30.000Z", "guild_status": "active"}}, {"total_battles": 9, "entered_battles": 9, "player": "hamsterpoweriii", "join_date": "2022-05-29T09:07:15.000Z", "wins": 6, "losses": 3, "draws": 0, "finish": 33, "meta_pts": 126, "meta_pts_float": 1486, "defeated": "bepoppin,uzuuzu,cepka,usay1907,sonyscv88,caffeinol", "fray_index": 3, "brawl_level": 3, "player_data": {"player": "hamsterpoweriii", "rating": 1962, "avatar_id": 5, "title_pre": null, "title_post": null, "display_name": null, "league": 7, "modern_league": 0, "collection_power": 483460, "starter_pack_purchase": true, "guild_id": "244a02b312201b4a1cca4f8b83eec767cf8af973", "guild_rank": 1, "guild_join_date": "2022-01-20T16:08:24.000Z", "guild_status": "active"}}, {"total_battles": 6, "entered_battles": 6, "player": "twinner", "join_date": "2022-05-29T09:08:42.000Z", "wins": 5, "losses": 1, "draws": 0, "finish": 36, "meta_pts": 66, "meta_pts_float": 4659, "defeated": "adonisabril,itachisusano,papadoge,neo2810,nrg", "fray_index": 11, "brawl_level": 3, "player_data": {"player": "twinner", "rating": 3791, "avatar_id": 0, "title_pre": null, "title_post": "The Untamed", "display_name": null, "league": 13, "modern_league": 0, "collection_power": 4740002, "starter_pack_purchase": true, "guild_id": "244a02b312201b4a1cca4f8b83eec767cf8af973", "guild_rank": 1, "guild_join_date": "2022-09-28T18:06:54.000Z", "guild_status": "active"}}, {"total_battles": 7, "entered_battles": 7, "player": "okean123", "join_date": "2022-05-29T09:07:51.000Z", "wins": 5, "losses": 2, "draws": 0, "finish": 39, "meta_pts": 90, "meta_pts_float": 2912, "defeated": "shanlay22,bluewing,colpak,gfriend96,hurax", "fray_index": 7, "brawl_level": 3, "player_data": {"player": "okean123", "rating": 2329, "avatar_id": 13, "title_pre": null, "title_post": null, "display_name": null, "league": 8, "modern_league": 0, "collection_power": 541415, "starter_pack_purchase": true, "guild_id": "244a02b312201b4a1cca4f8b83eec767cf8af973", "guild_rank": 4, "guild_join_date": "2019-07-31T12:38:36.000Z", "guild_status": "active"}}, {"total_battles": 8, "entered_battles": 8, "player": "danrid", "join_date": "2022-05-29T09:06:45.000Z", "wins": 5, "losses": 3, "draws": 0, "finish": 43, "meta_pts": 72, "meta_pts_float": 1756, "defeated": "egcho,splinterbin,nuttanan0298,kajko,bushwickvisual", "fray_index": 1, "brawl_level": 3, "player_data": {"player": "danrid", "rating": 0, "avatar_id": 15, "title_pre": null, "title_post": null, "display_name": null, "league": 0, "modern_league": 7, "collection_power": 221915, "starter_pack_purchase": true, "guild_id": "244a02b312201b4a1cca4f8b83eec767cf8af973", "guild_rank": 1, "guild_join_date": "2021-12-20T20:13:09.000Z", "guild_status": "active"}}, {"total_battles": 7, "entered_battles": 7, "player": "mr-waffles", "join_date": "2022-05-29T09:08:15.000Z", "wins": 4, "losses": 3, "draws": 0, "finish": 62, "meta_pts": 54, "meta_pts_float": 4526, "defeated": "kalyus,orrkis,iliqchuan,crypt0hog", "fray_index": 9, "brawl_level": 3, "player_data": {"player": "mr-waffles", "rating": 3535, "avatar_id": 9, "title_pre": null, "title_post": null, "display_name": null, "league": 12, "modern_league": 13, "collection_power": 1612647, "starter_pack_purchase": true, "guild_id": "244a02b312201b4a1cca4f8b83eec767cf8af973", "guild_rank": 1, "guild_join_date": "2022-03-28T08:28:09.000Z", "guild_status": "active"}}, {"total_battles": 8, "entered_battles": 8, "player": "flowshot", "join_date": "2022-05-29T09:06:27.000Z", "wins": 4, "losses": 4, "draws": 0, "finish": 70, "meta_pts": 42, "meta_pts_float": 2543, "defeated": "elrmapa,uglyman,saachi,darki456", "fray_index": 0, "brawl_level": 3, "player_data": {"player": "flowshot", "rating": 0, "avatar_id": 13, "title_pre": null, "title_post": null, "display_name": null, "league": 0, "modern_league": 7, "collection_power": 89270, "starter_pack_purchase": true, "guild_id": "244a02b312201b4a1cca4f8b83eec767cf8af973", "guild_rank": 1, "guild_join_date": "2022-06-09T11:07:30.000Z", "guild_status": "active"}}, {"total_battles": 9, "entered_battles": 9, "player": "nil-rem", "join_date": "2022-05-29T09:08:00.000Z", "wins": 4, "losses": 5, "draws": 0, "finish": 72, "meta_pts": 90, "meta_pts_float": 3885, "defeated": "forsakensushi,wombatoxl,ouubiot,no2", "fray_index": 8, "brawl_level": 3, "player_data": {"player": "nil-rem", "rating": 1400, "avatar_id": 14, "title_pre": null, "title_post": "The Legionnaire", "display_name": null, "league": 5, "modern_league": 11, "collection_power": 822315, "starter_pack_purchase": true, "guild_id": "244a02b312201b4a1cca4f8b83eec767cf8af973", "guild_rank": 1, "guild_join_date": "2021-08-12T00:07:00.000Z", "guild_status": "active"}}, {"total_battles": 9, "entered_battles": 9, "player": "unicron", "join_date": "2022-05-29T09:07:00.000Z", "wins": 4, "losses": 5, "draws": 0, "finish": 76, "meta_pts": 78, "meta_pts_float": 2848, "defeated": "urchintrader,gavino96,ssripraj,vip", "fray_index": 2, "brawl_level": 3, "player_data": {"player": "unicron", "rating": 2135, "avatar_id": 13, "title_pre": null, "title_post": null, "display_name": null, "league": 7, "modern_league": 0, "collection_power": 215615, "starter_pack_purchase": true, "guild_id": "244a02b312201b4a1cca4f8b83eec767cf8af973", "guild_rank": 1, "guild_join_date": "2019-08-29T17:37:18.000Z", "guild_status": "active"}}, {"total_battles": 8, "entered_battles": 8, "player": "dergefallene", "join_date": "2022-05-29T09:07:27.000Z", "wins": 3, "losses": 5, "draws": 0, "finish": 89, "meta_pts": 30, "meta_pts_float": 2902, "defeated": "chimmy9,pigben86,skymin", "fray_index": 4, "brawl_level": 3, "player_data": {"player": "dergefallene", "rating": 0, "avatar_id": 7, "title_pre": null, "title_post": null, "display_name": null, "league": 0, "modern_league": 6, "collection_power": 129085, "starter_pack_purchase": true, "guild_id": "244a02b312201b4a1cca4f8b83eec767cf8af973", "guild_rank": 1, "guild_join_date": "2022-02-05T20:16:09.000Z", "guild_status": "active"}}, {"total_battles": 8, "entered_battles": 8, "player": "samsemilia7", "join_date": "2022-05-29T09:07:39.000Z", "wins": 3, "losses": 5, "draws": 0, "finish": 92, "meta_pts": 18, "meta_pts_float": 3273, "defeated": "tradingideas,excellence42,karinxxl", "fray_index": 6, "brawl_level": 3, "player_data": {"player": "samsemilia7", "rating": 2290, "avatar_id": 9, "title_pre": null, "title_post": "The Legionnaire", "display_name": null, "league": 8, "modern_league": 0, "collection_power": 538945, "starter_pack_purchase": true, "guild_id": "244a02b312201b4a1cca4f8b83eec767cf8af973", "guild_rank": 3, "guild_join_date": "2019-07-30T20:33:15.000Z", "guild_status": "active"}}, {"total_battles": 5, "entered_battles": 5, "player": "beers", "join_date": "2022-05-29T09:09:15.000Z", "wins": 2, "losses": 3, "draws": 0, "finish": 105, "meta_pts": 24, "meta_pts_float": 2900, "defeated": "gormek,lostintime", "fray_index": 15, "brawl_level": 3, "player_data": {"player": "beers", "rating": 2113, "avatar_id": 0, "title_pre": null, "title_post": null, "display_name": null, "league": 7, "modern_league": 0, "collection_power": 1888100, "starter_pack_purchase": true, "guild_id": "89849b1562d843651ae4fef8000d43b57268f76b", "guild_rank": 2, "guild_join_date": "2022-09-04T22:22:24.000Z", "guild_status": "active"}}, {"total_battles": 6, "entered_battles": 6, "player": "happychillmore", "join_date": "2022-05-29T09:09:03.000Z", "wins": 2, "losses": 4, "draws": 0, "finish": 107, "meta_pts": 18, "meta_pts_float": 3191, "defeated": "pheels,cerser", "fray_index": 13, "brawl_level": 3, "player_data": {"player": "happychillmore", "rating": 2305, "avatar_id": 5, "title_pre": null, "title_post": null, "display_name": null, "league": 8, "modern_league": 0, "collection_power": 1081283, "starter_pack_purchase": true, "guild_id": "244a02b312201b4a1cca4f8b83eec767cf8af973", "guild_rank": 1, "guild_join_date": "2020-09-23T19:18:09.000Z", "guild_status": "active"}}], "guilds": [{"id": "30def23c7fb0958b011df5c39aedad6fd1fe34ba", "name": "The Anti Social Club", "data": "{\"crest\":{\"banner\":\"red\",\"decal\":\"skull\"}}", "total_payout": 67, "cycle": 86, "wins": 85, "losses": 37, "draws": 0, "pts": 255, "top_payout": 20, "other_payout": 47, "brawl_level": 4, "guild_rank": 15, "total_merits_payout": 73696, "member_merits_payout": 4606, "total_sps_payout": "0.000", "member_sps_payout": "0.000"}, {"id": "02ed5efea46e5b9a0b8ef3aedb26bb31f4e59dcc", "name": "PeakMonsters [Vikings]", "data": "{\"crest\":{\"banner\":\"blue\",\"decal\":\"sword\"}}", "total_payout": 57, "cycle": 86, "wins": 77, "losses": 45, "draws": 0, "pts": 231, "top_payout": 14, "other_payout": 43, "brawl_level": 4, "guild_rank": 33, "total_merits_payout": 51296, "member_merits_payout": 3206, "total_sps_payout": "0.000", "member_sps_payout": "0.000"}, {"id": "244a02b312201b4a1cca4f8b83eec767cf8af973", "name": "Legendary Whelps", "data": "{\"crest\":{\"banner\":\"yellow\",\"decal\":\"sword\"}}", "total_payout": 49, "cycle": 86, "wins": 75, "losses": 47, "draws": 0, "pts": 225, "top_payout": 7, "other_payout": 42, "brawl_level": 3, "guild_rank": 28, "total_merits_payout": 44096, "member_merits_payout": 2756, "total_sps_payout": "0.000", "member_sps_payout": "0.000"}, {"id": "60a0c13b6f13a61a424cd2a5a605ce91407709ec", "name": "Wax Street", "data": "{\"crest\":{\"banner\":\"blue\",\"decal\":\"skull\"}}", "total_payout": 36, "cycle": 86, "wins": 64, "losses": 52, "draws": 0, "pts": 192, "top_payout": 0, "other_payout": 36, "brawl_level": 3, "guild_rank": 117, "total_merits_payout": 30375, "member_merits_payout": 2025, "total_sps_payout": "0.000", "member_sps_payout": "0.000"}, {"id": "ddb09da326f7c20d0b3714a154e8aec45208c837", "name": "Legendary Raptors", "data": "{\"crest\":{\"banner\":\"yellow\",\"decal\":\"sword\"}}", "total_payout": 33, "cycle": 86, "wins": 60, "losses": 62, "draws": 0, "pts": 180, "top_payout": 0, "other_payout": 33, "brawl_level": 4, "guild_rank": 57, "total_merits_payout": 26400, "member_merits_payout": 1650, "total_sps_payout": "0.000", "member_sps_payout": "0.000"}, {"id": "13c9cdace559afffd0ae9105f8dd9d71517093db", "name": "PeakMonsters Embryon", "data": "{\"crest\":{\"banner\":\"teal\",\"decal\":\"skull\"}}", "total_payout": 31, "cycle": 86, "wins": 56, "losses": 65, "draws": 0, "pts": 168, "top_payout": 0, "other_payout": 31, "brawl_level": 3, "guild_rank": 60, "total_merits_payout": 27904, "member_merits_payout": 1744, "total_sps_payout": "0.000", "member_sps_payout": "0.000"}, {"id": "4f97fe48fd72ff437e9df6cceacbd732e352d6cf", "name": "Immortal Gods 2", "data": "{\"crest\":{\"banner\":\"black\",\"decal\":\"sword\"}}", "total_payout": 20, "cycle": 86, "wins": 36, "losses": 49, "draws": 0, "pts": 108, "top_payout": 0, "other_payout": 20, "brawl_level": 4, "guild_rank": 18, "total_merits_payout": 8750, "member_merits_payout": 1250, "total_sps_payout": "0.000", "member_sps_payout": "0.000"}, {"id": "63be801ae48313632ef5dd91ddb9a815387c2c16", "name": "TEAM KR", "data": "{\"crest\":{\"banner\":\"blue\",\"decal\":\"bolt\"}}", "total_payout": 19, "cycle": 86, "wins": 35, "losses": 63, "draws": 0, "pts": 105, "top_payout": 0, "other_payout": 19, "brawl_level": 3, "guild_rank": 45, "total_merits_payout": 8414, "member_merits_payout": 831, "total_sps_payout": "0.000", "member_sps_payout": "0.000"}, {"id": "f4201d176712b8adab92169c6148dc7b87509fc3", "name": "UT", "data": "{\"crest\":{\"banner\":\"red\",\"decal\":\"skull\"}}", "total_payout": 17, "cycle": 86, "wins": 30, "losses": 67, "draws": 0, "pts": 90, "top_payout": 0, "other_payout": 17, "brawl_level": 3, "guild_rank": 231, "total_merits_payout": 7440, "member_merits_payout": 744, "total_sps_payout": "0.000", "member_sps_payout": "0.000"}, {"id": "edc32f5e6e714d742463308e266165c30412c271", "name": "TeaRunFunToy CRYPTO SPS", "data": "{\"crest\":{\"banner\":\"yellow\",\"decal\":\"skull\"}}", "total_payout": 9, "cycle": 86, "wins": 17, "losses": 50, "draws": 0, "pts": 51, "top_payout": 0, "other_payout": 9, "brawl_level": 3, "guild_rank": 533, "total_merits_payout": 2364, "member_merits_payout": 394, "total_sps_payout": "0.000", "member_sps_payout": "0.000"}]}